{
  "name": "Hasan Efe Kocasu Portfolio",
  "description": "A modern and animated portfolio for showcasing Data Science, Statistics research, and GitHub projects.",
  "author": "Hasan Efe Kocasu",
  "url": "https://efekcss.github.io",
  "contact": "kocasuhasanefe@gmail.com",
  "technologies": [
    "HTML5",
    "Tailwind CSS (via CDN)",
    "Google Fonts",
    "Vanilla JavaScript",
    "GitHub Pages"
  ],
  "build": {
    "type": "static",
    "tooling": "none (static index.html served directly)"
  },
  "lastUpdated": "2026-02-27",
  "requestFramePermissions": []
}
